cdk_cloudformation_redis_cloudformation_prosubscription/__init__.py
cdk_cloudformation_redis_cloudformation_prosubscription/py.typed
cdk_cloudformation_redis_cloudformation_prosubscription/_jsii/__init__.py
cdk_cloudformation_redis_cloudformation_prosubscription/_jsii/redis-cloudformation-prosubscription@1.0.0-alpha.7.jsii.tgz
cdk_cloudformation_redis_cloudformation_prosubscription-1.0.0a7.dist-info/LICENSE
cdk_cloudformation_redis_cloudformation_prosubscription-1.0.0a7.dist-info/METADATA
cdk_cloudformation_redis_cloudformation_prosubscription-1.0.0a7.dist-info/WHEEL
cdk_cloudformation_redis_cloudformation_prosubscription-1.0.0a7.dist-info/top_level.txt
cdk_cloudformation_redis_cloudformation_prosubscription-1.0.0a7.dist-info/RECORD
